{
  "INJUSDT": {
    "last_signal": "buy",
    "last_alert_time": 1763313570.9076364
  },
  "FLOKIUSDT": {
    "last_signal": "buy",
    "last_alert_time": 1763313571.0453138
  },
  "RAYUSDT": {
    "last_signal": "buy",
    "last_alert_time": 1763313571.1555486
  },
  "ENSUSDT": {
    "last_signal": "buy",
    "last_alert_time": 1763313571.174618
  },
  "CFXUSDT": {
    "last_signal": "buy",
    "last_alert_time": 1763313571.213063
  },
  "EIGENUSDT": {
    "last_signal": "buy",
    "last_alert_time": 1763313571.3418932
  },
  "SUSDT": {
    "last_signal": "buy",
    "last_alert_time": 1763313571.3712778
  },
  "JASMYUSDT": {
    "last_signal": "buy",
    "last_alert_time": 1763313571.3951478
  },
  "BRETTUSDT": {
    "last_signal": "buy",
    "last_alert_time": 1763313571.4789636
  },
  "BERAUSDT": {
    "last_signal": "buy",
    "last_alert_time": 1763313571.6989448
  }
}