{
  "BEAMUSDT": {
    "last_signal": "buy",
    "last_alert_time": 1766089472.5743816
  },
  "BERAUSDT": {
    "last_signal": "buy",
    "last_alert_time": 1766089472.6411464
  },
  "SOLUSDT": {
    "last_signal": "buy",
    "last_alert_time": 1766090590.4428217
  },
  "ADAUSDT": {
    "last_signal": "buy",
    "last_alert_time": 1766090590.513769
  },
  "DOTUSDT": {
    "last_signal": "buy",
    "last_alert_time": 1766090590.5215502
  },
  "LTCUSDT": {
    "last_signal": "sell",
    "last_alert_time": 1766119655.1753833
  },
  "BNBUSDT": {
    "last_signal": "buy",
    "last_alert_time": 1766090590.5486465
  },
  "BTCUSDT": {
    "last_signal": "sell",
    "last_alert_time": 1766119655.182862
  },
  "XRPUSDT": {
    "last_signal": "buy",
    "last_alert_time": 1766090590.5623033
  },
  "HYPEUSDT": {
    "last_signal": "buy",
    "last_alert_time": 1766090590.5700455
  },
  "LINKUSDT": {
    "last_signal": "sell",
    "last_alert_time": 1766119655.4082627
  },
  "SUIUSDT": {
    "last_signal": "buy",
    "last_alert_time": 1766090590.832036
  },
  "HBARUSDT": {
    "last_signal": "buy",
    "last_alert_time": 1766090590.8385496
  },
  "CROUSDT": {
    "last_signal": "buy",
    "last_alert_time": 1766090590.8450687
  },
  "UNIUSDT": {
    "last_signal": "sell",
    "last_alert_time": 1766119655.4979005
  },
  "WLFIUSDT": {
    "last_signal": "buy",
    "last_alert_time": 1766090590.8595784
  },
  "AAVEUSDT": {
    "last_signal": "sell",
    "last_alert_time": 1766119655.5045085
  },
  "MNTUSDT": {
    "last_signal": "buy",
    "last_alert_time": 1766090591.0045927
  },
  "OKBUSDT": {
    "last_signal": "sell",
    "last_alert_time": 1766119655.6886756
  },
  "ASTERUSDT": {
    "last_signal": "buy",
    "last_alert_time": 1766090591.1381521
  },
  "TAOUSDT": {
    "last_signal": "buy",
    "last_alert_time": 1766090591.14252
  },
  "ENAUSDT": {
    "last_signal": "buy",
    "last_alert_time": 1766090591.163784
  },
  "PUMPUSDT": {
    "last_signal": "buy",
    "last_alert_time": 1766090591.1733913
  },
  "ONDOUSDT": {
    "last_signal": "buy",
    "last_alert_time": 1766090591.3122504
  },
  "ETCUSDT": {
    "last_signal": "sell",
    "last_alert_time": 1766119655.9634185
  },
  "PIUSDT": {
    "last_signal": "buy",
    "last_alert_time": 1766090591.4300072
  },
  "ICPUSDT": {
    "last_signal": "buy",
    "last_alert_time": 1766090591.4456887
  },
  "WLDUSDT": {
    "last_signal": "sell",
    "last_alert_time": 1766119656.0766747
  },
  "POLUSDT": {
    "last_signal": "buy",
    "last_alert_time": 1766090591.5823963
  },
  "KASUSDT": {
    "last_signal": "sell",
    "last_alert_time": 1766119656.257992
  },
  "PENGUUSDT": {
    "last_signal": "buy",
    "last_alert_time": 1766090591.7028701
  },
  "JUPUSDT": {
    "last_signal": "buy",
    "last_alert_time": 1766090591.7728956
  },
  "IMXUSDT": {
    "last_signal": "buy",
    "last_alert_time": 1766090591.7833009
  },
  "INJUSDT": {
    "last_signal": "buy",
    "last_alert_time": 1766090591.800842
  },
  "SEIUSDT": {
    "last_signal": "buy",
    "last_alert_time": 1766090591.855638
  },
  "CAKEUSDT": {
    "last_signal": "sell",
    "last_alert_time": 1766119656.5294435
  },
  "CRVUSDT": {
    "last_signal": "sell",
    "last_alert_time": 1766119656.628989
  },
  "SPXUSDT": {
    "last_signal": "sell",
    "last_alert_time": 1766119656.6542487
  },
  "PENDLEUSDT": {
    "last_signal": "buy",
    "last_alert_time": 1766090592.0587428
  },
  "WIFUSDT": {
    "last_signal": "sell",
    "last_alert_time": 1766119656.6711683
  },
  "FLOKIUSDT": {
    "last_signal": "sell",
    "last_alert_time": 1766119656.6856172
  },
  "RAYUSDT": {
    "last_signal": "buy",
    "last_alert_time": 1766090592.121359
  },
  "ENSUSDT": {
    "last_signal": "buy",
    "last_alert_time": 1766090592.1720781
  },
  "SUSDT": {
    "last_signal": "buy",
    "last_alert_time": 1766090592.214616
  },
  "JTOUSDT": {
    "last_signal": "sell",
    "last_alert_time": 1766119656.9397569
  },
  "FARTCOINUSDT": {
    "last_signal": "sell",
    "last_alert_time": 1766119656.9442606
  },
  "MUSDT": {
    "last_signal": "buy",
    "last_alert_time": 1766091314.644205
  },
  "JASMYUSDT": {
    "last_signal": "buy",
    "last_alert_time": 1766091315.4772573
  },
  "ETHUSDT": {
    "last_signal": "sell",
    "last_alert_time": 1766119655.2106986
  },
  "LDOUSDT": {
    "last_signal": "sell",
    "last_alert_time": 1766119656.410183
  },
  "CFXUSDT": {
    "last_signal": "sell",
    "last_alert_time": 1766119656.8501782
  },
  "EIGENUSDT": {
    "last_signal": "sell",
    "last_alert_time": 1766119656.915647
  }
}